{
    "model": {
        "name": "stonehenge_77x74x16_0.9_0",
        "camera_dims": [
            0.001,
            0.002
        ],
        "start_point": [
            -0.33,
            0.1,
            -0.45
        ],
        "goal_point": [
            0.22,
            -0.16,
            -0.45
        ],
        "max_time_per_path": 5
    },
    "planners": {
        "EST": {
            "status": "Successful",
            "total_time_taken": 0,
            "num_paths": 1,
            "average_path_length": 0.93,
            "shortest_path_length": 0.93,
            "longest_path_length": 0.93,
            "path_length_std_dev": 0.0,
            "average_time_per_path": 0.11,
            "time_per_path_std_dev": 0.0,
            "paths": [
                {
                    "id": 0,
                    "length": 0.93,
                    "duration": 0.11
                }
            ]
        },
        "KPIECE1": {
            "status": "Successful",
            "total_time_taken": 0,
            "num_paths": 1,
            "average_path_length": 0.78,
            "shortest_path_length": 0.78,
            "longest_path_length": 0.78,
            "path_length_std_dev": 0.0,
            "average_time_per_path": 0.03,
            "time_per_path_std_dev": 0.0,
            "paths": [
                {
                    "id": 0,
                    "length": 0.78,
                    "duration": 0.03
                }
            ]
        },
        "LTLPlanner": {
            "status": "Failed",
            "error_message": "Error occurred for planner LTLPlanner: name 'om' is not defined"
        },
        "PDST": {
            "status": "Successful",
            "total_time_taken": 0,
            "num_paths": 1,
            "average_path_length": 0.93,
            "shortest_path_length": 0.93,
            "longest_path_length": 0.93,
            "path_length_std_dev": 0.0,
            "average_time_per_path": 0.06,
            "time_per_path_std_dev": 0.0,
            "paths": [
                {
                    "id": 0,
                    "length": 0.93,
                    "duration": 0.06
                }
            ]
        },
        "RRT": {
            "status": "Successful",
            "total_time_taken": 0,
            "num_paths": 1,
            "average_path_length": 0.78,
            "shortest_path_length": 0.78,
            "longest_path_length": 0.78,
            "path_length_std_dev": 0.0,
            "average_time_per_path": 0.03,
            "time_per_path_std_dev": 0.0,
            "paths": [
                {
                    "id": 0,
                    "length": 0.78,
                    "duration": 0.03
                }
            ]
        },
        "SST": {
            "status": "Failed",
            "error_message": "No solution found for attempt 0."
        },
        "Syclop": {
            "status": "Failed",
            "error_message": "Error occurred for planner Syclop: Python argument types in"
        },
        "AITstar": {
            "status": "Failed",
            "error_message": null
        },
        "AnytimePathShorteing": {
            "status": "Failed",
            "error_message": "Error occurred for planner AnytimePathShorteing: name 'om' is not defined"
        },
        "BFMT": {
            "status": "Failed",
            "error_message": "Error occurred for planner BFMT: could not broadcast input array from shape (0,) into shape (3,)"
        },
        "BiEST": {
            "status": "Successful",
            "total_time_taken": 0,
            "num_paths": 1,
            "average_path_length": 0.82,
            "shortest_path_length": 0.82,
            "longest_path_length": 0.82,
            "path_length_std_dev": 0.0,
            "average_time_per_path": 0.06,
            "time_per_path_std_dev": 0.0,
            "paths": [
                {
                    "id": 0,
                    "length": 0.82,
                    "duration": 0.06
                }
            ]
        },
        "BiTRRT": {
            "status": "Failed",
            "error_message": "Error occurred for planner BiTRRT: name 'om' is not defined"
        },
        "BITstar": {
            "status": "Successful",
            "total_time_taken": 0,
            "num_paths": 1,
            "average_path_length": 0.77,
            "shortest_path_length": 0.77,
            "longest_path_length": 0.77,
            "path_length_std_dev": 0.0,
            "average_time_per_path": 5.02,
            "time_per_path_std_dev": 0.0,
            "paths": [
                {
                    "id": 0,
                    "length": 0.77,
                    "duration": 5.02
                }
            ]
        },
        "BKPIECE1": {
            "status": "Successful",
            "total_time_taken": 0,
            "num_paths": 1,
            "average_path_length": 0.92,
            "shortest_path_length": 0.92,
            "longest_path_length": 0.92,
            "path_length_std_dev": 0.0,
            "average_time_per_path": 0.07,
            "time_per_path_std_dev": 0.0,
            "paths": [
                {
                    "id": 0,
                    "length": 0.92,
                    "duration": 0.07
                }
            ]
        },
        "CForest": {
            "status": "Failed",
            "error_message": "Error occurred for planner CForest: name 'om' is not defined"
        },
        "FMT": {
            "status": "Failed",
            "error_message": "Error occurred for planner FMT: could not broadcast input array from shape (0,) into shape (3,)"
        },
        "LazyLBTRRT": {
            "status": "Successful",
            "total_time_taken": 0,
            "num_paths": 1,
            "average_path_length": 0.8,
            "shortest_path_length": 0.8,
            "longest_path_length": 0.8,
            "path_length_std_dev": 0.0,
            "average_time_per_path": 5.02,
            "time_per_path_std_dev": 0.0,
            "paths": [
                {
                    "id": 0,
                    "length": 0.8,
                    "duration": 5.02
                }
            ]
        },
        "LazyPRM": {
            "status": "Successful",
            "total_time_taken": 0,
            "num_paths": 1,
            "average_path_length": 1.04,
            "shortest_path_length": 1.04,
            "longest_path_length": 1.04,
            "path_length_std_dev": 0.0,
            "average_time_per_path": 0.11,
            "time_per_path_std_dev": 0.0,
            "paths": [
                {
                    "id": 0,
                    "length": 1.04,
                    "duration": 0.11
                }
            ]
        },
        "LazyRRT": {
            "status": "Successful",
            "total_time_taken": 0,
            "num_paths": 1,
            "average_path_length": 0.79,
            "shortest_path_length": 0.79,
            "longest_path_length": 0.79,
            "path_length_std_dev": 0.0,
            "average_time_per_path": 0.16,
            "time_per_path_std_dev": 0.0,
            "paths": [
                {
                    "id": 0,
                    "length": 0.79,
                    "duration": 0.16
                }
            ]
        },
        "LBKPIECE1": {
            "status": "Successful",
            "total_time_taken": 0,
            "num_paths": 1,
            "average_path_length": 0.93,
            "shortest_path_length": 0.93,
            "longest_path_length": 0.93,
            "path_length_std_dev": 0.0,
            "average_time_per_path": 0.14,
            "time_per_path_std_dev": 0.0,
            "paths": [
                {
                    "id": 0,
                    "length": 0.93,
                    "duration": 0.14
                }
            ]
        },
        "LBTRRT": {
            "status": "Successful",
            "total_time_taken": 0,
            "num_paths": 1,
            "average_path_length": 0.8,
            "shortest_path_length": 0.8,
            "longest_path_length": 0.8,
            "path_length_std_dev": 0.0,
            "average_time_per_path": 5.02,
            "time_per_path_std_dev": 0.0,
            "paths": [
                {
                    "id": 0,
                    "length": 0.8,
                    "duration": 5.02
                }
            ]
        },
        "LightningRetrieveRepair": {
            "status": "Failed",
            "error_message": "Error occurred for planner LightningRetrieveRepair: name 'om' is not defined"
        },
        "PRM": {
            "status": "Successful",
            "total_time_taken": 0,
            "num_paths": 1,
            "average_path_length": 0.8,
            "shortest_path_length": 0.8,
            "longest_path_length": 0.8,
            "path_length_std_dev": 0.0,
            "average_time_per_path": 0.11,
            "time_per_path_std_dev": 0.0,
            "paths": [
                {
                    "id": 0,
                    "length": 0.8,
                    "duration": 0.11
                }
            ]
        },
        "ProjEST": {
            "status": "Successful",
            "total_time_taken": 0,
            "num_paths": 1,
            "average_path_length": 1.01,
            "shortest_path_length": 1.01,
            "longest_path_length": 1.01,
            "path_length_std_dev": 0.0,
            "average_time_per_path": 0.08,
            "time_per_path_std_dev": 0.0,
            "paths": [
                {
                    "id": 0,
                    "length": 1.01,
                    "duration": 0.08
                }
            ]
        },
        "pRRT": {
            "status": "Failed",
            "error_message": "Error occurred for planner pRRT: name 'om' is not defined"
        },
        "pSBL": {
            "status": "Failed",
            "error_message": "Error occurred for planner pSBL: name 'om' is not defined"
        },
        "RLRT": {
            "status": "Failed",
            "error_message": "Error occurred for planner RLRT: name 'om' is not defined"
        },
        "RRTConnect": {
            "status": "Successful",
            "total_time_taken": 0,
            "num_paths": 1,
            "average_path_length": 0.79,
            "shortest_path_length": 0.79,
            "longest_path_length": 0.79,
            "path_length_std_dev": 0.0,
            "average_time_per_path": 0.07,
            "time_per_path_std_dev": 0.0,
            "paths": [
                {
                    "id": 0,
                    "length": 0.79,
                    "duration": 0.07
                }
            ]
        },
        "RRTstar": {
            "status": "Successful",
            "total_time_taken": 0,
            "num_paths": 1,
            "average_path_length": 0.77,
            "shortest_path_length": 0.77,
            "longest_path_length": 0.77,
            "path_length_std_dev": 0.0,
            "average_time_per_path": 5.03,
            "time_per_path_std_dev": 0.0,
            "paths": [
                {
                    "id": 0,
                    "length": 0.77,
                    "duration": 5.03
                }
            ]
        },
        "RRTXstatic": {
            "status": "Successful",
            "total_time_taken": 0,
            "num_paths": 1,
            "average_path_length": 0.77,
            "shortest_path_length": 0.77,
            "longest_path_length": 0.77,
            "path_length_std_dev": 0.0,
            "average_time_per_path": 5.02,
            "time_per_path_std_dev": 0.0,
            "paths": [
                {
                    "id": 0,
                    "length": 0.77,
                    "duration": 5.02
                }
            ]
        },
        "SBL": {
            "status": "Successful",
            "total_time_taken": 0,
            "num_paths": 1,
            "average_path_length": 0.77,
            "shortest_path_length": 0.77,
            "longest_path_length": 0.77,
            "path_length_std_dev": 0.0,
            "average_time_per_path": 0.05,
            "time_per_path_std_dev": 0.0,
            "paths": [
                {
                    "id": 0,
                    "length": 0.77,
                    "duration": 0.05
                }
            ]
        },
        "SPARS": {
            "status": "Failed",
            "error_message": null
        },
        "SPARSdb": {
            "status": "Failed",
            "error_message": "Error occurred for planner SPARSdb: name 'om' is not defined"
        },
        "SPARStwo": {
            "status": "Failed",
            "error_message": null
        },
        "STRIDE": {
            "status": "Successful",
            "total_time_taken": 0,
            "num_paths": 1,
            "average_path_length": 0.79,
            "shortest_path_length": 0.79,
            "longest_path_length": 0.79,
            "path_length_std_dev": 0.0,
            "average_time_per_path": 0.04,
            "time_per_path_std_dev": 0.0,
            "paths": [
                {
                    "id": 0,
                    "length": 0.79,
                    "duration": 0.04
                }
            ]
        },
        "STRRTstar": {
            "status": "Failed",
            "error_message": "Error occurred for planner STRRTstar: name 'om' is not defined"
        },
        "ThunderRetrieveRepair": {
            "status": "Failed",
            "error_message": "Error occurred for planner ThunderRetrieveRepair: name 'om' is not defined"
        },
        "TRRT": {
            "status": "Successful",
            "total_time_taken": 0,
            "num_paths": 1,
            "average_path_length": 0.78,
            "shortest_path_length": 0.78,
            "longest_path_length": 0.78,
            "path_length_std_dev": 0.0,
            "average_time_per_path": 0.03,
            "time_per_path_std_dev": 0.0,
            "paths": [
                {
                    "id": 0,
                    "length": 0.78,
                    "duration": 0.03
                }
            ]
        },
        "TSRRT": {
            "status": "Failed",
            "error_message": "Error occurred for planner TSRRT: name 'om' is not defined"
        },
        "XXL": {
            "status": "Failed",
            "error_message": "Error occurred for planner XXL: name 'om' is not defined"
        }
    }
}