{
    "model": {
        "name": "cuboids",
        "camera_bounds": [
            0.005,
            0.005,
            0.02
        ],
        "start_point": [
            -0.33,
            0.1,
            -0.44
        ],
        "goal_point": [
            0.22,
            -0.16,
            -0.44
        ],
        "max_time_per_path": 5
    },
    "planners": {
        "PRM": {
            "status": "Successful",
            "total_time_taken": 2.16,
            "num_paths": 1,
            "average_path_length": 0.82,
            "shortest_path_length": 0.82,
            "longest_path_length": 0.82,
            "path_length_std_dev": 0.0,
            "average_time_per_path": 2.15,
            "time_per_path_std_dev": 0.0,
            "paths": [
                {
                    "id": 0,
                    "length": 0.82,
                    "duration": 2.15
                }
            ]
        },
        "LazyPRM": {
            "status": "Failed",
            "error_message": "Error occurred for planner LazyPRM: local variable 'path' referenced before assignment"
        },
        "PRMstar": {
            "status": "Successful",
            "total_time_taken": 5.07,
            "num_paths": 1,
            "average_path_length": 0.65,
            "shortest_path_length": 0.65,
            "longest_path_length": 0.65,
            "path_length_std_dev": 0.0,
            "average_time_per_path": 5.07,
            "time_per_path_std_dev": 0.0,
            "paths": [
                {
                    "id": 0,
                    "length": 0.65,
                    "duration": 5.07
                }
            ]
        },
        "LazyPRMstar": {
            "status": "Successful",
            "total_time_taken": 5.04,
            "num_paths": 1,
            "average_path_length": 0.81,
            "shortest_path_length": 0.81,
            "longest_path_length": 0.81,
            "path_length_std_dev": 0.0,
            "average_time_per_path": 5.04,
            "time_per_path_std_dev": 0.0,
            "paths": [
                {
                    "id": 0,
                    "length": 0.81,
                    "duration": 5.04
                }
            ]
        },
        "SPARS": {
            "status": "Failed",
            "error_message": null
        },
        "SPARS2": {
            "status": "Failed",
            "error_message": "Error occurred for planner SPARS2: 'NoneType' object is not callable"
        },
        "RRT": {
            "status": "Successful",
            "total_time_taken": 0.09,
            "num_paths": 1,
            "average_path_length": 0.9,
            "shortest_path_length": 0.9,
            "longest_path_length": 0.9,
            "path_length_std_dev": 0.0,
            "average_time_per_path": 0.09,
            "time_per_path_std_dev": 0.0,
            "paths": [
                {
                    "id": 0,
                    "length": 0.9,
                    "duration": 0.09
                }
            ]
        },
        "RRTConnect": {
            "status": "Successful",
            "total_time_taken": 0.1,
            "num_paths": 1,
            "average_path_length": 0.86,
            "shortest_path_length": 0.86,
            "longest_path_length": 0.86,
            "path_length_std_dev": 0.0,
            "average_time_per_path": 0.09,
            "time_per_path_std_dev": 0.0,
            "paths": [
                {
                    "id": 0,
                    "length": 0.86,
                    "duration": 0.09
                }
            ]
        },
        "RRTstar": {
            "status": "Successful",
            "total_time_taken": 5.05,
            "num_paths": 1,
            "average_path_length": 0.78,
            "shortest_path_length": 0.78,
            "longest_path_length": 0.78,
            "path_length_std_dev": 0.0,
            "average_time_per_path": 5.05,
            "time_per_path_std_dev": 0.0,
            "paths": [
                {
                    "id": 0,
                    "length": 0.78,
                    "duration": 5.05
                }
            ]
        },
        "SST": {
            "status": "Failed",
            "error_message": "Error occurred for planner SST: local variable 'path' referenced before assignment"
        },
        "T-RRT": {
            "status": "Failed",
            "error_message": "Error occurred for planner T-RRT: 'NoneType' object is not callable"
        },
        "VF-RRT": {
            "status": "Failed",
            "error_message": "Error occurred for planner VF-RRT: 'NoneType' object is not callable"
        },
        "pRRT": {
            "status": "Failed",
            "error_message": "Error occurred for planner pRRT: 'NoneType' object is not callable"
        },
        "LazyRRT": {
            "status": "Failed",
            "error_message": "Error occurred for planner LazyRRT: local variable 'path' referenced before assignment"
        },
        "TSRRT": {
            "status": "Failed",
            "error_message": "Error occurred for planner TSRRT: 'NoneType' object is not callable"
        },
        "EST": {
            "status": "Successful",
            "total_time_taken": 0.47,
            "num_paths": 1,
            "average_path_length": 0.84,
            "shortest_path_length": 0.84,
            "longest_path_length": 0.84,
            "path_length_std_dev": 0.0,
            "average_time_per_path": 0.47,
            "time_per_path_std_dev": 0.0,
            "paths": [
                {
                    "id": 0,
                    "length": 0.84,
                    "duration": 0.47
                }
            ]
        },
        "KPIECE": {
            "status": "Failed",
            "error_message": "Error occurred for planner KPIECE: 'NoneType' object is not callable"
        },
        "BKPIECE": {
            "status": "Failed",
            "error_message": "Error occurred for planner BKPIECE: 'NoneType' object is not callable"
        },
        "LBKPIECE": {
            "status": "Failed",
            "error_message": "Error occurred for planner LBKPIECE: 'NoneType' object is not callable"
        },
        "STRIDE": {
            "status": "Successful",
            "total_time_taken": 0.21,
            "num_paths": 1,
            "average_path_length": 1.08,
            "shortest_path_length": 1.08,
            "longest_path_length": 1.08,
            "path_length_std_dev": 0.0,
            "average_time_per_path": 0.21,
            "time_per_path_std_dev": 0.0,
            "paths": [
                {
                    "id": 0,
                    "length": 1.08,
                    "duration": 0.21
                }
            ]
        },
        "PDST": {
            "status": "Successful",
            "total_time_taken": 0.13,
            "num_paths": 1,
            "average_path_length": 1.21,
            "shortest_path_length": 1.21,
            "longest_path_length": 1.21,
            "path_length_std_dev": 0.0,
            "average_time_per_path": 0.13,
            "time_per_path_std_dev": 0.0,
            "paths": [
                {
                    "id": 0,
                    "length": 1.21,
                    "duration": 0.13
                }
            ]
        },
        "FMTstar": {
            "status": "Failed",
            "error_message": "Error occurred for planner FMTstar: 'NoneType' object is not callable"
        },
        "BMFTstar": {
            "status": "Failed",
            "error_message": "Error occurred for planner BMFTstar: 'NoneType' object is not callable"
        },
        "QRRT": {
            "status": "Failed",
            "error_message": "Error occurred for planner QRRT: 'NoneType' object is not callable"
        },
        "QRRTstar": {
            "status": "Failed",
            "error_message": "Error occurred for planner QRRTstar: 'NoneType' object is not callable"
        },
        "QMP": {
            "status": "Failed",
            "error_message": "Error occurred for planner QMP: 'NoneType' object is not callable"
        },
        "QMPstar": {
            "status": "Failed",
            "error_message": "Error occurred for planner QMPstar: 'NoneType' object is not callable"
        },
        "RRTsharp": {
            "status": "Successful",
            "total_time_taken": 5.03,
            "num_paths": 1,
            "average_path_length": 0.77,
            "shortest_path_length": 0.77,
            "longest_path_length": 0.77,
            "path_length_std_dev": 0.0,
            "average_time_per_path": 5.03,
            "time_per_path_std_dev": 0.0,
            "paths": [
                {
                    "id": 0,
                    "length": 0.77,
                    "duration": 5.03
                }
            ]
        },
        "RRTX": {
            "status": "Failed",
            "error_message": "Error occurred for planner RRTX: 'NoneType' object is not callable"
        },
        "InformedRRTstar": {
            "status": "Successful",
            "total_time_taken": 5.05,
            "num_paths": 1,
            "average_path_length": 0.77,
            "shortest_path_length": 0.77,
            "longest_path_length": 0.77,
            "path_length_std_dev": 0.0,
            "average_time_per_path": 5.05,
            "time_per_path_std_dev": 0.0,
            "paths": [
                {
                    "id": 0,
                    "length": 0.77,
                    "duration": 5.05
                }
            ]
        },
        "BITstar": {
            "status": "Successful",
            "total_time_taken": 5.08,
            "num_paths": 1,
            "average_path_length": 0.74,
            "shortest_path_length": 0.74,
            "longest_path_length": 0.74,
            "path_length_std_dev": 0.0,
            "average_time_per_path": 5.08,
            "time_per_path_std_dev": 0.0,
            "paths": [
                {
                    "id": 0,
                    "length": 0.74,
                    "duration": 5.08
                }
            ]
        },
        "ABITstar": {
            "status": "Successful",
            "total_time_taken": 5.09,
            "num_paths": 1,
            "average_path_length": 0.77,
            "shortest_path_length": 0.77,
            "longest_path_length": 0.77,
            "path_length_std_dev": 0.0,
            "average_time_per_path": 5.09,
            "time_per_path_std_dev": 0.0,
            "paths": [
                {
                    "id": 0,
                    "length": 0.77,
                    "duration": 5.09
                }
            ]
        },
        "AITstar": {
            "status": "Failed",
            "error_message": null
        },
        "LBTRRT": {
            "status": "Successful",
            "total_time_taken": 5.05,
            "num_paths": 1,
            "average_path_length": 0.91,
            "shortest_path_length": 0.91,
            "longest_path_length": 0.91,
            "path_length_std_dev": 0.0,
            "average_time_per_path": 5.05,
            "time_per_path_std_dev": 0.0,
            "paths": [
                {
                    "id": 0,
                    "length": 0.91,
                    "duration": 5.05
                }
            ]
        },
        "ST-RRTstar": {
            "status": "Failed",
            "error_message": "Error occurred for planner ST-RRTstar: 'NoneType' object is not callable"
        },
        "CForest": {
            "status": "Failed",
            "error_message": "Error occurred for planner CForest: 'NoneType' object is not callable"
        },
        "APS": {
            "status": "Failed",
            "error_message": "Error occurred for planner APS: 'NoneType' object is not callable"
        },
        "SyCLoP": {
            "status": "Failed",
            "error_message": "Error occurred for planner SyCLoP: 'NoneType' object is not callable"
        },
        "LTLPlanner": {
            "status": "Failed",
            "error_message": "Error occurred for planner LTLPlanner: 'NoneType' object is not callable"
        },
        "SPQRstar": {
            "status": "Failed",
            "error_message": "Error occurred for planner SPQRstar: 'NoneType' object is not callable"
        }
    }
}